{
  "intents": [
    {
      "intent": "DebitCardPurchaseIntent",
      "slots":[
        {
          "name": "Account",
          "type": "AccountType"
        },
        {
          "name": "Vendor",
          "type": "VendorType"
        },
        {
          "name": "StartDate",
          "type": "AMAZON.DATE"
        },
        {
          "name": "EndDate",
          "type": "AMAZON.DATE"
        }
      ]
    },
    {
      "intent": "TransactionsIntent",
      "slots":[
        {
          "name": "Account",
          "type": "AccountType"
        },
        {
          "name": "Transaction",
          "type": "TransactionType"
        },
        {
          "name": "StartDate",
          "type": "AMAZON.DATE"
        },
        {
          "name": "EndDate",
          "type": "AMAZON.DATE"
        }
      ]
    },
    {
      "intent": "DepositsIntent",
      "slots":[
        {
          "name": "Account",
          "type": "AccountType"
        },
        {
          "name": "StartDate",
          "type": "AMAZON.DATE"
        },
        {
          "name": "EndDate",
          "type": "AMAZON.DATE"
        }
      ]
    },
    {
      "intent": "OrderCheckbookIntent",
      "slots":[
        {
          "name": "Account",
          "type": "AccountType"
        },
        {
          "name": "StaringCheckNumber",
          "type": "AMAZON.NUMBER"
        }
      ]
    },
    {
      "intent": "TellAccountSummaryIntent",
      "slots":[
        {
          "name": "Account",
          "type": "AccountType"
        }]
    },
    {
      "intent": "TextAccountSummaryIntent",
      "slots":[
        {
          "name": "Account",
          "type": "AccountType"
        }]
    },
    {
      "intent": "BankATMLocationsIntent"
    },
    {
      "intent": "ReferralStatusIntent"
    },
    {
      "intent": "SupportedFunctionsIntent"
    },
    {
      "intent": "DontKnowIntent"
    },
    {
      "intent": "AMAZON.StartOverIntent"
    },
    {
      "intent": "AMAZON.RepeatIntent"
    },
    {
      "intent": "AMAZON.HelpIntent"
    },
    {
      "intent": "AMAZON.YesIntent"
    },
    {
      "intent": "AMAZON.NoIntent"
    },
    {
      "intent": "AMAZON.StopIntent"
    },
    {
      "intent": "AMAZON.CancelIntent"
    }
  ]
}